{".class":"MypyFile","_fullname":"zonevu.DataModels.Geosteering.Conditioning","future_import_flags":[],"is_partial_stub_package":false,"is_stub":false,"names":{".class":"SymbolTable","Conditioning":{".class":"SymbolTableNode","kind":"Gdef","node":{".class":"TypeInfo","_promote":[],"abstract_attributes":[],"alt_promote":null,"bases":["builtins.object"],"dataclass_transform_spec":null,"declared_metaclass":null,"defn":{".class":"ClassDef","fullname":"zonevu.DataModels.Geosteering.Conditioning.Conditioning","name":"Conditioning","type_vars":[]},"deletable_attributes":[],"flags":[],"fullname":"zonevu.DataModels.Geosteering.Conditioning.Conditioning","has_param_spec_type":false,"metaclass_type":null,"metadata":{"dataclass":{"attributes":[{"alias":null,"column":4,"has_default":true,"is_in_init":true,"is_init_var":false,"is_neither_frozen_nor_nonfrozen":false,"kw_only":false,"line":13,"name":"AmplClip","type":"builtins.bool"},{"alias":null,"column":4,"has_default":true,"is_in_init":true,"is_init_var":false,"is_neither_frozen_nor_nonfrozen":false,"kw_only":false,"line":14,"name":"AmplClipRangeMin","type":{".class":"UnionType","items":["builtins.float",{".class":"NoneType"}]}},{"alias":null,"column":4,"has_default":true,"is_in_init":true,"is_init_var":false,"is_neither_frozen_nor_nonfrozen":false,"kw_only":false,"line":15,"name":"AmplClipRangeMax","type":{".class":"UnionType","items":["builtins.float",{".class":"NoneType"}]}},{"alias":null,"column":4,"has_default":true,"is_in_init":true,"is_init_var":false,"is_neither_frozen_nor_nonfrozen":false,"kw_only":false,"line":16,"name":"AmplClipInclusiveNotExclusive","type":{".class":"UnionType","items":["builtins.bool",{".class":"NoneType"}]}},{"alias":null,"column":4,"has_default":true,"is_in_init":true,"is_init_var":false,"is_neither_frozen_nor_nonfrozen":false,"kw_only":false,"line":19,"name":"MDClip","type":"builtins.bool"},{"alias":null,"column":4,"has_default":true,"is_in_init":true,"is_init_var":false,"is_neither_frozen_nor_nonfrozen":false,"kw_only":false,"line":20,"name":"MDClipRangeMin","type":{".class":"UnionType","items":["builtins.float",{".class":"NoneType"}]}},{"alias":null,"column":4,"has_default":true,"is_in_init":true,"is_init_var":false,"is_neither_frozen_nor_nonfrozen":false,"kw_only":false,"line":21,"name":"MDClipRangeMax","type":{".class":"UnionType","items":["builtins.float",{".class":"NoneType"}]}},{"alias":null,"column":4,"has_default":true,"is_in_init":true,"is_init_var":false,"is_neither_frozen_nor_nonfrozen":false,"kw_only":false,"line":22,"name":"MDClipInclusiveNotExclusive","type":{".class":"UnionType","items":["builtins.bool",{".class":"NoneType"}]}},{"alias":null,"column":4,"has_default":true,"is_in_init":true,"is_init_var":false,"is_neither_frozen_nor_nonfrozen":false,"kw_only":false,"line":25,"name":"Despike","type":"builtins.bool"},{"alias":null,"column":4,"has_default":true,"is_in_init":true,"is_init_var":false,"is_neither_frozen_nor_nonfrozen":false,"kw_only":false,"line":26,"name":"VarianceThreshold","type":{".class":"UnionType","items":["builtins.float",{".class":"NoneType"}]}},{"alias":null,"column":4,"has_default":true,"is_in_init":true,"is_init_var":false,"is_neither_frozen_nor_nonfrozen":false,"kw_only":false,"line":28,"name":"DespikeLen","type":{".class":"UnionType","items":["builtins.int",{".class":"NoneType"}]}},{"alias":null,"column":4,"has_default":true,"is_in_init":true,"is_init_var":false,"is_neither_frozen_nor_nonfrozen":false,"kw_only":false,"line":31,"name":"Interpolate","type":"builtins.bool"},{"alias":null,"column":4,"has_default":true,"is_in_init":true,"is_init_var":false,"is_neither_frozen_nor_nonfrozen":false,"kw_only":false,"line":32,"name":"MaxGap","type":{".class":"UnionType","items":["builtins.int",{".class":"NoneType"}]}},{"alias":null,"column":4,"has_default":true,"is_in_init":true,"is_init_var":false,"is_neither_frozen_nor_nonfrozen":false,"kw_only":false,"line":35,"name":"Smooth","type":"builtins.bool"},{"alias":null,"column":4,"has_default":true,"is_in_init":true,"is_init_var":false,"is_neither_frozen_nor_nonfrozen":false,"kw_only":false,"line":36,"name":"SmoothingLen","type":{".class":"UnionType","items":["builtins.int",{".class":"NoneType"}]}},{"alias":null,"column":4,"has_default":true,"is_in_init":true,"is_init_var":false,"is_neither_frozen_nor_nonfrozen":false,"kw_only":false,"line":39,"name":"Normalize","type":"builtins.bool"},{"alias":null,"column":4,"has_default":true,"is_in_init":true,"is_init_var":false,"is_neither_frozen_nor_nonfrozen":false,"kw_only":false,"line":40,"name":"Bias","type":{".class":"UnionType","items":["builtins.float",{".class":"NoneType"}]}},{"alias":null,"column":4,"has_default":true,"is_in_init":true,"is_init_var":false,"is_neither_frozen_nor_nonfrozen":false,"kw_only":false,"line":41,"name":"Scalar","type":{".class":"UnionType","items":["builtins.float",{".class":"NoneType"}]}}],"frozen":false},"dataclass_tag":{}},"module_name":"zonevu.DataModels.Geosteering.Conditioning","mro":["zonevu.DataModels.Geosteering.Conditioning.Conditioning","builtins.object"],"names":{".class":"SymbolTable","AmplClip":{".class":"SymbolTableNode","kind":"Mdef","node":{".class":"Var","flags":["is_initialized_in_class","is_ready","has_explicit_value"],"fullname":"zonevu.DataModels.Geosteering.Conditioning.Conditioning.AmplClip","name":"AmplClip","type":"builtins.bool"}},"AmplClipInclusiveNotExclusive":{".class":"SymbolTableNode","kind":"Mdef","node":{".class":"Var","flags":["is_initialized_in_class","is_ready","has_explicit_value"],"fullname":"zonevu.DataModels.Geosteering.Conditioning.Conditioning.AmplClipInclusiveNotExclusive","name":"AmplClipInclusiveNotExclusive","type":{".class":"UnionType","items":["builtins.bool",{".class":"NoneType"}]}}},"AmplClipRangeMax":{".class":"SymbolTableNode","kind":"Mdef","node":{".class":"Var","flags":["is_initialized_in_class","is_ready","has_explicit_value"],"fullname":"zonevu.DataModels.Geosteering.Conditioning.Conditioning.AmplClipRangeMax","name":"AmplClipRangeMax","type":{".class":"UnionType","items":["builtins.float",{".class":"NoneType"}]}}},"AmplClipRangeMin":{".class":"SymbolTableNode","kind":"Mdef","node":{".class":"Var","flags":["is_initialized_in_class","is_ready","has_explicit_value"],"fullname":"zonevu.DataModels.Geosteering.Conditioning.Conditioning.AmplClipRangeMin","name":"AmplClipRangeMin","type":{".class":"UnionType","items":["builtins.float",{".class":"NoneType"}]}}},"Bias":{".class":"SymbolTableNode","kind":"Mdef","node":{".class":"Var","flags":["is_initialized_in_class","is_ready","has_explicit_value"],"fullname":"zonevu.DataModels.Geosteering.Conditioning.Conditioning.Bias","name":"Bias","type":{".class":"UnionType","items":["builtins.float",{".class":"NoneType"}]}}},"Despike":{".class":"SymbolTableNode","kind":"Mdef","node":{".class":"Var","flags":["is_initialized_in_class","is_ready","has_explicit_value"],"fullname":"zonevu.DataModels.Geosteering.Conditioning.Conditioning.Despike","name":"Despike","type":"builtins.bool"}},"DespikeLen":{".class":"SymbolTableNode","kind":"Mdef","node":{".class":"Var","flags":["is_initialized_in_class","is_ready","has_explicit_value"],"fullname":"zonevu.DataModels.Geosteering.Conditioning.Conditioning.DespikeLen","name":"DespikeLen","type":{".class":"UnionType","items":["builtins.int",{".class":"NoneType"}]}}},"Interpolate":{".class":"SymbolTableNode","kind":"Mdef","node":{".class":"Var","flags":["is_initialized_in_class","is_ready","has_explicit_value"],"fullname":"zonevu.DataModels.Geosteering.Conditioning.Conditioning.Interpolate","name":"Interpolate","type":"builtins.bool"}},"MDClip":{".class":"SymbolTableNode","kind":"Mdef","node":{".class":"Var","flags":["is_initialized_in_class","is_ready","has_explicit_value"],"fullname":"zonevu.DataModels.Geosteering.Conditioning.Conditioning.MDClip","name":"MDClip","type":"builtins.bool"}},"MDClipInclusiveNotExclusive":{".class":"SymbolTableNode","kind":"Mdef","node":{".class":"Var","flags":["is_initialized_in_class","is_ready","has_explicit_value"],"fullname":"zonevu.DataModels.Geosteering.Conditioning.Conditioning.MDClipInclusiveNotExclusive","name":"MDClipInclusiveNotExclusive","type":{".class":"UnionType","items":["builtins.bool",{".class":"NoneType"}]}}},"MDClipRangeMax":{".class":"SymbolTableNode","kind":"Mdef","node":{".class":"Var","flags":["is_initialized_in_class","is_ready","has_explicit_value"],"fullname":"zonevu.DataModels.Geosteering.Conditioning.Conditioning.MDClipRangeMax","name":"MDClipRangeMax","type":{".class":"UnionType","items":["builtins.float",{".class":"NoneType"}]}}},"MDClipRangeMin":{".class":"SymbolTableNode","kind":"Mdef","node":{".class":"Var","flags":["is_initialized_in_class","is_ready","has_explicit_value"],"fullname":"zonevu.DataModels.Geosteering.Conditioning.Conditioning.MDClipRangeMin","name":"MDClipRangeMin","type":{".class":"UnionType","items":["builtins.float",{".class":"NoneType"}]}}},"MaxGap":{".class":"SymbolTableNode","kind":"Mdef","node":{".class":"Var","flags":["is_initialized_in_class","is_ready","has_explicit_value"],"fullname":"zonevu.DataModels.Geosteering.Conditioning.Conditioning.MaxGap","name":"MaxGap","type":{".class":"UnionType","items":["builtins.int",{".class":"NoneType"}]}}},"Normalize":{".class":"SymbolTableNode","kind":"Mdef","node":{".class":"Var","flags":["is_initialized_in_class","is_ready","has_explicit_value"],"fullname":"zonevu.DataModels.Geosteering.Conditioning.Conditioning.Normalize","name":"Normalize","type":"builtins.bool"}},"Scalar":{".class":"SymbolTableNode","kind":"Mdef","node":{".class":"Var","flags":["is_initialized_in_class","is_ready","has_explicit_value"],"fullname":"zonevu.DataModels.Geosteering.Conditioning.Conditioning.Scalar","name":"Scalar","type":{".class":"UnionType","items":["builtins.float",{".class":"NoneType"}]}}},"Smooth":{".class":"SymbolTableNode","kind":"Mdef","node":{".class":"Var","flags":["is_initialized_in_class","is_ready","has_explicit_value"],"fullname":"zonevu.DataModels.Geosteering.Conditioning.Conditioning.Smooth","name":"Smooth","type":"builtins.bool"}},"SmoothingLen":{".class":"SymbolTableNode","kind":"Mdef","node":{".class":"Var","flags":["is_initialized_in_class","is_ready","has_explicit_value"],"fullname":"zonevu.DataModels.Geosteering.Conditioning.Conditioning.SmoothingLen","name":"SmoothingLen","type":{".class":"UnionType","items":["builtins.int",{".class":"NoneType"}]}}},"VarianceThreshold":{".class":"SymbolTableNode","kind":"Mdef","node":{".class":"Var","flags":["is_initialized_in_class","is_ready","has_explicit_value"],"fullname":"zonevu.DataModels.Geosteering.Conditioning.Conditioning.VarianceThreshold","name":"VarianceThreshold","type":{".class":"UnionType","items":["builtins.float",{".class":"NoneType"}]}}},"__dataclass_fields__":{".class":"SymbolTableNode","kind":"Mdef","node":{".class":"Var","flags":["is_classvar","is_ready"],"fullname":"zonevu.DataModels.Geosteering.Conditioning.Conditioning.__dataclass_fields__","name":"__dataclass_fields__","type":{".class":"Instance","args":["builtins.str",{".class":"Instance","args":[{".class":"AnyType","missing_import_name":null,"source_any":null,"type_of_any":2}],"type_ref":"dataclasses.Field"}],"type_ref":"builtins.dict"}},"plugin_generated":true},"__init__":{".class":"SymbolTableNode","kind":"Mdef","node":{".class":"FuncDef","abstract_status":0,"arg_kinds":[0,1,1,1,1,1,1,1,1,1,1,1,1,1,1,1,1,1,1],"arg_names":["self","AmplClip","AmplClipRangeMin","AmplClipRangeMax","AmplClipInclusiveNotExclusive","MDClip","MDClipRangeMin","MDClipRangeMax","MDClipInclusiveNotExclusive","Despike","VarianceThreshold","DespikeLen","Interpolate","MaxGap","Smooth","SmoothingLen","Normalize","Bias","Scalar"],"dataclass_transform_spec":null,"flags":[],"fullname":"zonevu.DataModels.Geosteering.Conditioning.Conditioning.__init__","name":"__init__","type":{".class":"CallableType","arg_kinds":[0,1,1,1,1,1,1,1,1,1,1,1,1,1,1,1,1,1,1],"arg_names":["self","AmplClip","AmplClipRangeMin","AmplClipRangeMax","AmplClipInclusiveNotExclusive","MDClip","MDClipRangeMin","MDClipRangeMax","MDClipInclusiveNotExclusive","Despike","VarianceThreshold","DespikeLen","Interpolate","MaxGap","Smooth","SmoothingLen","Normalize","Bias","Scalar"],"arg_types":["zonevu.DataModels.Geosteering.Conditioning.Conditioning","builtins.bool",{".class":"UnionType","items":["builtins.float",{".class":"NoneType"}]},{".class":"UnionType","items":["builtins.float",{".class":"NoneType"}]},{".class":"UnionType","items":["builtins.bool",{".class":"NoneType"}]},"builtins.bool",{".class":"UnionType","items":["builtins.float",{".class":"NoneType"}]},{".class":"UnionType","items":["builtins.float",{".class":"NoneType"}]},{".class":"UnionType","items":["builtins.bool",{".class":"NoneType"}]},"builtins.bool",{".class":"UnionType","items":["builtins.float",{".class":"NoneType"}]},{".class":"UnionType","items":["builtins.int",{".class":"NoneType"}]},"builtins.bool",{".class":"UnionType","items":["builtins.int",{".class":"NoneType"}]},"builtins.bool",{".class":"UnionType","items":["builtins.int",{".class":"NoneType"}]},"builtins.bool",{".class":"UnionType","items":["builtins.float",{".class":"NoneType"}]},{".class":"UnionType","items":["builtins.float",{".class":"NoneType"}]}],"bound_args":[],"def_extras":{},"fallback":"builtins.function","from_concatenate":false,"implicit":false,"imprecise_arg_kinds":false,"is_ellipsis_args":false,"name":"__init__ of Conditioning","ret_type":{".class":"NoneType"},"type_guard":null,"unpack_kwargs":false,"variables":[]}},"plugin_generated":true},"__match_args__":{".class":"SymbolTableNode","kind":"Mdef","node":{".class":"Var","flags":["is_ready","allow_incompatible_override"],"fullname":"zonevu.DataModels.Geosteering.Conditioning.Conditioning.__match_args__","name":"__match_args__","type":{".class":"TupleType","implicit":false,"items":[{".class":"LiteralType","fallback":"builtins.str","value":"AmplClip"},{".class":"LiteralType","fallback":"builtins.str","value":"AmplClipRangeMin"},{".class":"LiteralType","fallback":"builtins.str","value":"AmplClipRangeMax"},{".class":"LiteralType","fallback":"builtins.str","value":"AmplClipInclusiveNotExclusive"},{".class":"LiteralType","fallback":"builtins.str","value":"MDClip"},{".class":"LiteralType","fallback":"builtins.str","value":"MDClipRangeMin"},{".class":"LiteralType","fallback":"builtins.str","value":"MDClipRangeMax"},{".class":"LiteralType","fallback":"builtins.str","value":"MDClipInclusiveNotExclusive"},{".class":"LiteralType","fallback":"builtins.str","value":"Despike"},{".class":"LiteralType","fallback":"builtins.str","value":"VarianceThreshold"},{".class":"LiteralType","fallback":"builtins.str","value":"DespikeLen"},{".class":"LiteralType","fallback":"builtins.str","value":"Interpolate"},{".class":"LiteralType","fallback":"builtins.str","value":"MaxGap"},{".class":"LiteralType","fallback":"builtins.str","value":"Smooth"},{".class":"LiteralType","fallback":"builtins.str","value":"SmoothingLen"},{".class":"LiteralType","fallback":"builtins.str","value":"Normalize"},{".class":"LiteralType","fallback":"builtins.str","value":"Bias"},{".class":"LiteralType","fallback":"builtins.str","value":"Scalar"}],"partial_fallback":{".class":"Instance","args":[{".class":"AnyType","missing_import_name":null,"source_any":null,"type_of_any":6}],"type_ref":"builtins.tuple"}}},"plugin_generated":true},"__mypy-replace":{".class":"SymbolTableNode","kind":"Mdef","node":{".class":"Decorator","func":{".class":"FuncDef","abstract_status":0,"arg_kinds":[5,5,5,5,5,5,5,5,5,5,5,5,5,5,5,5,5,5],"arg_names":["AmplClip","AmplClipRangeMin","AmplClipRangeMax","AmplClipInclusiveNotExclusive","MDClip","MDClipRangeMin","MDClipRangeMax","MDClipInclusiveNotExclusive","Despike","VarianceThreshold","DespikeLen","Interpolate","MaxGap","Smooth","SmoothingLen","Normalize","Bias","Scalar"],"dataclass_transform_spec":null,"flags":["is_static","is_decorated"],"fullname":"zonevu.DataModels.Geosteering.Conditioning.Conditioning.__mypy-replace","name":"__mypy-replace","type":{".class":"CallableType","arg_kinds":[5,5,5,5,5,5,5,5,5,5,5,5,5,5,5,5,5,5],"arg_names":["AmplClip","AmplClipRangeMin","AmplClipRangeMax","AmplClipInclusiveNotExclusive","MDClip","MDClipRangeMin","MDClipRangeMax","MDClipInclusiveNotExclusive","Despike","VarianceThreshold","DespikeLen","Interpolate","MaxGap","Smooth","SmoothingLen","Normalize","Bias","Scalar"],"arg_types":["builtins.bool",{".class":"UnionType","items":["builtins.float",{".class":"NoneType"}]},{".class":"UnionType","items":["builtins.float",{".class":"NoneType"}]},{".class":"UnionType","items":["builtins.bool",{".class":"NoneType"}]},"builtins.bool",{".class":"UnionType","items":["builtins.float",{".class":"NoneType"}]},{".class":"UnionType","items":["builtins.float",{".class":"NoneType"}]},{".class":"UnionType","items":["builtins.bool",{".class":"NoneType"}]},"builtins.bool",{".class":"UnionType","items":["builtins.float",{".class":"NoneType"}]},{".class":"UnionType","items":["builtins.int",{".class":"NoneType"}]},"builtins.bool",{".class":"UnionType","items":["builtins.int",{".class":"NoneType"}]},"builtins.bool",{".class":"UnionType","items":["builtins.int",{".class":"NoneType"}]},"builtins.bool",{".class":"UnionType","items":["builtins.float",{".class":"NoneType"}]},{".class":"UnionType","items":["builtins.float",{".class":"NoneType"}]}],"bound_args":[],"def_extras":{},"fallback":"builtins.function","from_concatenate":false,"implicit":false,"imprecise_arg_kinds":false,"is_ellipsis_args":false,"name":"__mypy-replace of Conditioning","ret_type":{".class":"NoneType"},"type_guard":null,"unpack_kwargs":false,"variables":[]}},"is_overload":false,"var":{".class":"Var","flags":["is_staticmethod","is_ready"],"fullname":"zonevu.DataModels.Geosteering.Conditioning.Conditioning.__mypy-replace","name":"__mypy-replace","type":{".class":"CallableType","arg_kinds":[5,5,5,5,5,5,5,5,5,5,5,5,5,5,5,5,5,5],"arg_names":["AmplClip","AmplClipRangeMin","AmplClipRangeMax","AmplClipInclusiveNotExclusive","MDClip","MDClipRangeMin","MDClipRangeMax","MDClipInclusiveNotExclusive","Despike","VarianceThreshold","DespikeLen","Interpolate","MaxGap","Smooth","SmoothingLen","Normalize","Bias","Scalar"],"arg_types":["builtins.bool",{".class":"UnionType","items":["builtins.float",{".class":"NoneType"}]},{".class":"UnionType","items":["builtins.float",{".class":"NoneType"}]},{".class":"UnionType","items":["builtins.bool",{".class":"NoneType"}]},"builtins.bool",{".class":"UnionType","items":["builtins.float",{".class":"NoneType"}]},{".class":"UnionType","items":["builtins.float",{".class":"NoneType"}]},{".class":"UnionType","items":["builtins.bool",{".class":"NoneType"}]},"builtins.bool",{".class":"UnionType","items":["builtins.float",{".class":"NoneType"}]},{".class":"UnionType","items":["builtins.int",{".class":"NoneType"}]},"builtins.bool",{".class":"UnionType","items":["builtins.int",{".class":"NoneType"}]},"builtins.bool",{".class":"UnionType","items":["builtins.int",{".class":"NoneType"}]},"builtins.bool",{".class":"UnionType","items":["builtins.float",{".class":"NoneType"}]},{".class":"UnionType","items":["builtins.float",{".class":"NoneType"}]}],"bound_args":[],"def_extras":{},"fallback":"builtins.function","from_concatenate":false,"implicit":false,"imprecise_arg_kinds":false,"is_ellipsis_args":false,"name":"__mypy-replace of Conditioning","ret_type":{".class":"NoneType"},"type_guard":null,"unpack_kwargs":false,"variables":[]}}},"plugin_generated":true}},"self_type":{".class":"TypeVarType","default":{".class":"AnyType","missing_import_name":null,"source_any":null,"type_of_any":4},"fullname":"zonevu.DataModels.Geosteering.Conditioning.Conditioning.Self","id":0,"name":"Self","namespace":"","upper_bound":"zonevu.DataModels.Geosteering.Conditioning.Conditioning","values":[],"variance":0},"slots":null,"tuple_type":null,"type_vars":[],"typeddict_type":null}},"LetterCase":{".class":"SymbolTableNode","cross_ref":"dataclasses_json.cfg.LetterCase","kind":"Gdef"},"Optional":{".class":"SymbolTableNode","cross_ref":"typing.Optional","kind":"Gdef"},"__annotations__":{".class":"SymbolTableNode","kind":"Gdef","node":{".class":"Var","flags":["is_ready"],"fullname":"zonevu.DataModels.Geosteering.Conditioning.__annotations__","name":"__annotations__","type":{".class":"Instance","args":["builtins.str",{".class":"AnyType","missing_import_name":null,"source_any":null,"type_of_any":6}],"type_ref":"builtins.dict"}}},"__doc__":{".class":"SymbolTableNode","kind":"Gdef","node":{".class":"Var","flags":["is_ready"],"fullname":"zonevu.DataModels.Geosteering.Conditioning.__doc__","name":"__doc__","type":"builtins.str"}},"__file__":{".class":"SymbolTableNode","kind":"Gdef","node":{".class":"Var","flags":["is_ready"],"fullname":"zonevu.DataModels.Geosteering.Conditioning.__file__","name":"__file__","type":"builtins.str"}},"__name__":{".class":"SymbolTableNode","kind":"Gdef","node":{".class":"Var","flags":["is_ready"],"fullname":"zonevu.DataModels.Geosteering.Conditioning.__name__","name":"__name__","type":"builtins.str"}},"__package__":{".class":"SymbolTableNode","kind":"Gdef","node":{".class":"Var","flags":["is_ready"],"fullname":"zonevu.DataModels.Geosteering.Conditioning.__package__","name":"__package__","type":"builtins.str"}},"config":{".class":"SymbolTableNode","cross_ref":"dataclasses_json.cfg.config","kind":"Gdef"},"dataclass":{".class":"SymbolTableNode","cross_ref":"dataclasses.dataclass","kind":"Gdef"},"dataclass_json":{".class":"SymbolTableNode","cross_ref":"dataclasses_json.api.dataclass_json","kind":"Gdef"},"field":{".class":"SymbolTableNode","cross_ref":"dataclasses.field","kind":"Gdef"}},"path":"C:\\Users\\PeterFlanagan\\source\\repos\\ZonevuPythonSDK\\zonevu\\zonevu\\DataModels\\Geosteering\\Conditioning.py"}